Atom.cp312-win_amd64.pyd
Atom.pyi
Chem_Atom-0.0.5.dist-info/METADATA
Chem_Atom-0.0.5.dist-info/WHEEL
Chem_Atom-0.0.5.dist-info/top_level.txt
Chem_Atom-0.0.5.dist-info/RECORD
