Metadata-Version: 2.1
Name: Chem-Atom
Version: 0.0.5
Summary: Chem-Atom is a library used for storing and editing chemical structural formulas. It provides an easy-to-use class Atom, which primarily stores atoms to achieve functions such as structure registration, modification, and conversion.
Home-page: https://github.com/God-Forever/Chem-Adom
Author: GodForever
Author-email: GodForever2022@outlook.com
Project-URL: Source, https://github.com/God-Forever/Chem-Adom
Platform: Windows
Classifier: Development Status :: 3 - Alpha
Classifier: Intended Audience :: Developers
Classifier: Topic :: Software Development :: Build Tools
Classifier: License :: OSI Approved :: MIT License
Classifier: Programming Language :: Python :: 3
Classifier: Programming Language :: Python :: 3.8
Classifier: Programming Language :: Python :: 3.9
Classifier: Programming Language :: Python :: 3.10
Classifier: Programming Language :: Python :: 3.11
Classifier: Programming Language :: Python :: 3.12
Requires-Python: >=3.8
